{
  "type": "Feature",
  "properties": {
    "iso:country":"SO",
    "ne:ADM0CAP":0.0,
    "ne:ADM0NAME":"Somaliland",
    "ne:ADM0_A3":"SOL",
    "ne:ADMIN1_COD":0,
    "ne:CAPALT":0,
    "ne:CHANGED":0,
    "ne:CHECKME":0,
    "ne:COMPARE":0,
    "ne:DIFFASCII":0,
    "ne:ELEVATION":0.0,
    "ne:FEATURECLA":"Populated place",
    "ne:GEONAMEID":-1,
    "ne:GEONAMESNO":"No GeoNames match due to small population, not in GeoNames, or poor NEV placement.",
    "ne:GN_POP":0,
    "ne:GTOPO30":0.0,
    "ne:ISO_A2":"-99",
    "ne:LABELRANK":0,
    "ne:LATITUDE":9.940413,
    "ne:LONGITUDE":43.180041,
    "ne:LS_MATCH":1,
    "ne:LS_NAME":"Boorama",
    "ne:MAX_AREAKM":26.0,
    "ne:MAX_AREAMI":10.0,
    "ne:MAX_BBXMAX":43.2,
    "ne:MAX_BBXMIN":43.133333,
    "ne:MAX_BBYMAX":9.991667,
    "ne:MAX_BBYMIN":9.925,
    "ne:MAX_NATSCA":20.0,
    "ne:MAX_PERKM":35.0,
    "ne:MAX_PERMI":22.0,
    "ne:MAX_POP10":67664,
    "ne:MAX_POP20":67664,
    "ne:MAX_POP300":0,
    "ne:MAX_POP310":0,
    "ne:MAX_POP50":0,
    "ne:MEAN_BBXC":43.168952,
    "ne:MEAN_BBYC":9.95793,
    "ne:MEGACITY":0,
    "ne:MIN_AREAKM":26.0,
    "ne:MIN_AREAMI":10.0,
    "ne:MIN_BBXMAX":43.2,
    "ne:MIN_BBXMIN":43.133333,
    "ne:MIN_BBYMAX":9.991667,
    "ne:MIN_BBYMIN":9.925,
    "ne:MIN_PERKM":35.0,
    "ne:MIN_PERMI":22.0,
    "ne:NAME":"Boorama",
    "ne:NAMEASCII":"Boorama",
    "ne:NAMEDIFF":0,
    "ne:NATSCALE":20,
    "ne:POP1950":0,
    "ne:POP1955":0,
    "ne:POP1960":0,
    "ne:POP1965":0,
    "ne:POP1970":0,
    "ne:POP1975":0,
    "ne:POP1980":0,
    "ne:POP1985":0,
    "ne:POP1990":0,
    "ne:POP1995":0,
    "ne:POP2000":0,
    "ne:POP2005":0,
    "ne:POP2010":0,
    "ne:POP2015":0,
    "ne:POP2020":0,
    "ne:POP2025":0,
    "ne:POP2050":0,
    "ne:POP_MAX":67664,
    "ne:POP_MIN":67664,
    "ne:POP_OTHER":68879,
    "ne:RANK_MAX":8,
    "ne:RANK_MIN":8,
    "ne:SCALERANK":7,
    "ne:SOV0NAME":"Somaliland",
    "ne:SOV_A3":"SOL",
    "ne:UN_FID":0,
    "ne:UN_LAT":0.0,
    "ne:UN_LONG":0.0,
    "ne:WORLDCITY":0,
    "ne:min_zoom":6.7,
    "wof:name":"Boorama",
    "wof:placetype":"locality"
},
  "geometry": {"coordinates":[43.1800410550731,9.94041261691825],"type":"Point"}
}